spotlight/__init__.py
spotlight/main.py
spotlight/automap/automap.py
spotlight/common/ErrRetry.py
spotlight/common/ForSAP.py
spotlight/common/colors.py
spotlight/common/common.py
spotlight/common/myFileDialog.py
spotlight/common/protoSelector.py
spotlight/concatText/__init__.py
spotlight/concatText/concatText.py
spotlight/concatText/concatTextTest.py
spotlight/import2df/import2df.py
spotlight/merge/merge.py
spotlight/merge/setkey.py
spotlight/modify/applyDC.py
spotlight/modify/automanual.py
spotlight/modify/createUnsigned.py
spotlight/modify/dropColumn.py
spotlight/modify/dropDuplicate.py
spotlight/modify/fillna.py
spotlight/modify/m100.py
spotlight/modify/minus.py
spotlight/modify/modify.py
spotlight/modify/replace.py
spotlight/old/00 LEAD.xlsx
spotlight/old/23 적재_txt2df2db_batch.py
spotlight/old/31 검증_Table 후처리.sql
spotlight/old/32 검증_DATA검증.sql
spotlight/old/41 추출.sql
spotlight/old/42 coa 2 db.py
spotlight/old/90 기타_test.py
spotlight/old/90 기타_데이터클렌징_tsv2df.py
spotlight/old/90 기타_참고_검증_Table정합성.sql
spotlight/old/91 기타_AMI 추가.py
spotlight/old/91 기타_검증_ami 관련.sql
spotlight/old/coa.json
spotlight/read/__init__.py
spotlight/read/read.py
spotlight/recon/recon.py
spotlight/save/save.py
spotlight/save/savePart.py
spotlight/txt2db/__init__.py
spotlight/txt2db/txt2db.py
spotlight/txt2db/mod/dbcon.py
spotlight/txt2db/mod/df2db.py
spotlight/txt2db/mod/txt2df.py
spotlighter-0.0.8.dist-info/METADATA
spotlighter-0.0.8.dist-info/WHEEL
spotlighter-0.0.8.dist-info/RECORD
