Metadata-Version: 2.1
Name: spotlighter
Version: 0.0.8
Summary: auto-preprocess GL to upload spotlight
Author-email: "Sgt. Park" <kinphw@naver.com>
Requires-Dist: numpy>=1.26.2
Requires-Dist: pandas>=2.1.2
Requires-Dist: pymysql>=1.1.0
Requires-Dist: pyodbc>=5.0.1
Requires-Dist: sqlalchemy>=2.0.23
Requires-Dist: tqdm>=4.66.1
